{
  "base16": {
    "base00": "#2a303c",
    "base01": "#3B4252",
    "base02": "#434C5E",
    "base03": "#4C566A",
    "base04": "#566074",
    "base05": "#bfc5d0",
    "base06": "#c7cdd8",
    "base07": "#ced4df",
    "base08": "#d57780",
    "base09": "#e39a83",
    "base0A": "#EBCB8B",
    "base0B": "#A3BE8C",
    "base0C": "#97b7d7",
    "base0D": "#81A1C1",
    "base0E": "#B48EAD",
    "base0F": "#d57780"
  },
  "base30": {
    "baby_pink": "#de878f",
    "black": "#2a303c",
    "black2": "#2f3541",
    "blue": "#7797b7",
    "cyan": "#9aafe6",
    "dark_purple": "#B48EAD",
    "darker_black": "#252b37",
    "folder_bg": "#7797b7",
    "green": "#A3BE8C",
    "grey": "#4d535f",
    "grey_fg": "#545a66",
    "grey_fg2": "#595f6b",
    "light_grey": "#606672",
    "lightbg": "#3f4551",
    "line": "#414753",
    "nord_blue": "#81A1C1",
    "one_bg": "#343a46",
    "one_bg2": "#3e4450",
    "one_bg3": "#484e5a",
    "orange": "#e39a83",
    "pink": "#da838b",
    "pmenu_bg": "#A3BE8C",
    "purple": "#aab1be",
    "red": "#d57780",
    "statusline_bg": "#333945",
    "sun": "#e1c181",
    "teal": "#6484a4",
    "vibrant_green": "#afca98",
    "white": "#D8DEE9",
    "yellow": "#EBCB8B"
  },
  "name": "onenord",
  "theme": {
    "name": "onenord",
    "type": "dark"
  },
  "type": "dark"
}
